PSELPyDeviceCamera/__init__.py
PSELPyDeviceCamera/__version__.py
PSELPyDeviceCamera/_devicecamera_mixin.py
PSELPyDeviceCamera/devicecamera.py
PSELPyDeviceCamera-0.1.1.dist-info/LICENSE.txt
PSELPyDeviceCamera-0.1.1.dist-info/METADATA
PSELPyDeviceCamera-0.1.1.dist-info/WHEEL
PSELPyDeviceCamera-0.1.1.dist-info/top_level.txt
PSELPyDeviceCamera-0.1.1.dist-info/RECORD
